MANIFEST.in
README.rst
setup.py
collective/__init__.py
collective.slideshare.egg-info/PKG-INFO
collective.slideshare.egg-info/SOURCES.txt
collective.slideshare.egg-info/dependency_links.txt
collective.slideshare.egg-info/entry_points.txt
collective.slideshare.egg-info/namespace_packages.txt
collective.slideshare.egg-info/not-zip-safe
collective.slideshare.egg-info/requires.txt
collective.slideshare.egg-info/top_level.txt
collective/slideshare/README.txt
collective/slideshare/Tests.txt
collective/slideshare/__init__.py
collective/slideshare/config.py
collective/slideshare/configure.zcml
collective/slideshare/handlers.py
collective/slideshare/interfaces.py
collective/slideshare/utils.py
collective/slideshare/vocabularies.py
collective/slideshare/browser/__init__.py
collective/slideshare/browser/configure.zcml
collective/slideshare/browser/controlpanel.py
collective/slideshare/browser/forms.py
collective/slideshare/browser/slideshare.png
collective/slideshare/browser/slideshareview.pt
collective/slideshare/browser/views.py
collective/slideshare/profiles/default/actions.xml
collective/slideshare/profiles/default/browserlayer.xml
collective/slideshare/profiles/default/controlpanel.xml
collective/slideshare/profiles/default/metadata.xml
collective/slideshare/profiles/default/registry.xml
collective/slideshare/profiles/default/types/File.xml
collective/slideshare/profiles/default/types/Link.xml
collective/slideshare/tests/__init__.py
collective/slideshare/tests/base.py
collective/slideshare/tests/test_doctest.py
docs/CHANGES.txt
docs/CONTRIBUTORS.txt
docs/HISTORY.txt
docs/INSTALL.txt
docs/LICENSE.txt