Metadata-Version: 1.1
Name: collective.slideshare
Version: 0.3
Summary: Easily publish your presentations on slideshare
Home-page: http://plone.org/products/collective.slideshare
Author: Christian Ledermann
Author-email: christian.ledermann@gmail.com
License: GPL
Keywords: slideshare api
Platform: UNKNOWN
Classifier: Framework :: Plone
Classifier: License :: OSI Approved :: GNU General Public License (GPL)
Classifier: Framework :: Plone :: 4.2
Classifier: Framework :: Plone :: 4.3
Classifier: Programming Language :: Python
Classifier: Development Status :: 4 - Beta
Classifier: Operating System :: OS Independent
